scrapytest/__init__.py
scrapytest/cli.py
scrapytest/default_settings.py
scrapytest/runner.py
scrapytest/spec.py
scrapytest/tests.py
scrapytest/utils.py
scrapytest/validate.py
scrapytest-0.1.dist-info/METADATA
scrapytest-0.1.dist-info/WHEEL
scrapytest-0.1.dist-info/entry_points.txt
scrapytest-0.1.dist-info/top_level.txt
scrapytest-0.1.dist-info/RECORD
