Metadata-Version: 2.1
Name: scrapytest
Version: 0.1
Summary: scrapy output testing framework
Home-page: https://gitlab.com/granitosaurus/scrapy-test
Author: granitosaurus
Author-email: granitosaurus@pm.me
License: GPLv3
Platform: UNKNOWN
